odoo/addons/stock_move_common_dest/README.rst
odoo/addons/stock_move_common_dest/__init__.py
odoo/addons/stock_move_common_dest/__manifest__.py
odoo/addons/stock_move_common_dest/i18n/it.po
odoo/addons/stock_move_common_dest/i18n/stock_move_common_dest.pot
odoo/addons/stock_move_common_dest/models/__init__.py
odoo/addons/stock_move_common_dest/models/stock_move.py
odoo/addons/stock_move_common_dest/readme/CONTRIBUTORS.rst
odoo/addons/stock_move_common_dest/readme/DESCRIPTION.rst
odoo/addons/stock_move_common_dest/static/description/icon.png
odoo/addons/stock_move_common_dest/static/description/index.html
odoo/addons/stock_move_common_dest/tests/__init__.py
odoo/addons/stock_move_common_dest/tests/test_move_common_dest.py
odoo/addons/stock_move_common_dest/views/stock_move.xml
odoo14_addon_stock_move_common_dest-14.0.1.0.1.dist-info/METADATA
odoo14_addon_stock_move_common_dest-14.0.1.0.1.dist-info/WHEEL
odoo14_addon_stock_move_common_dest-14.0.1.0.1.dist-info/top_level.txt
odoo14_addon_stock_move_common_dest-14.0.1.0.1.dist-info/RECORD
